{
    "description": "Describes a schedule",
    "type": "object",
    "properties": {
        "frequency": {
            "$ref" : "https://raw.githubusercontent.com/beckn/protocol-specifications/core-v0.9.1/core/v0/schema/duration.json"
        },
        "holidays": {
            "type": "array",
            "items": {
                "type": "string",
                "format" : "date-time"
            }
        },
        "times": {
            "type" : "array",
            "items" : {
                "type" : "string",
                "format" : "date-time"
            }
        }
    }
}